omnifetch/__init__.py
omnifetch/cache_manager.py
omnifetch/data_manager.py
omnifetch/data_source_config.py
omnifetch/storage_backends.py
omnifetch/sync_manager.py
omnifetch/adapters/__init__.py
omnifetch/adapters/yaml_config.py
omnifetch-1.0.0.dist-info/licenses/LICENSE
omnifetch-1.0.0.dist-info/METADATA
omnifetch-1.0.0.dist-info/WHEEL
omnifetch-1.0.0.dist-info/top_level.txt
omnifetch-1.0.0.dist-info/RECORD
