Metadata-Version: 2.4
Name: omnifetch
Version: 1.0.0
Summary: Multi-source data retrieval with intelligent caching and storage backends
Home-page: https://github.com/deinnovatie/omnifetch
Author: Marco Bonoli
Author-email: Marco Bonoli <marco@deinnovatie.com>
License: MIT
Project-URL: Homepage, https://github.com/deinnovatie/omnifetch
Project-URL: Documentation, https://github.com/deinnovatie/omnifetch#readme
Project-URL: Repository, https://github.com/deinnovatie/omnifetch
Project-URL: Bug Tracker, https://github.com/deinnovatie/omnifetch/issues
Keywords: data-management,caching,storage,ibm-cos,cloud-storage,ttl,multi-source
Classifier: Development Status :: 4 - Beta
Classifier: Intended Audience :: Developers
Classifier: Intended Audience :: Science/Research
Classifier: License :: OSI Approved :: MIT License
Classifier: Operating System :: OS Independent
Classifier: Programming Language :: Python :: 3
Classifier: Programming Language :: Python :: 3.8
Classifier: Programming Language :: Python :: 3.9
Classifier: Programming Language :: Python :: 3.10
Classifier: Programming Language :: Python :: 3.11
Requires-Python: >=3.8
License-File: LICENSE
Requires-Dist: ibm-cos-sdk>=2.13.3
Requires-Dist: filelock>=3.13.1
Requires-Dist: pandas>=2.1.4
Requires-Dist: xarray>=2023.12.0
Requires-Dist: netCDF4>=1.6.5
Requires-Dist: pyarrow>=14.0.1
Requires-Dist: pyyaml>=6.0.1
Provides-Extra: dev
Requires-Dist: pytest>=7.4.0; extra == "dev"
Requires-Dist: pytest-cov>=4.1.0; extra == "dev"
Requires-Dist: black>=23.0.0; extra == "dev"
Requires-Dist: ruff>=0.1.0; extra == "dev"
Requires-Dist: mypy>=1.5.0; extra == "dev"
Provides-Extra: docs
Requires-Dist: sphinx>=7.0.0; extra == "docs"
Requires-Dist: sphinx-rtd-theme>=1.3.0; extra == "docs"
Dynamic: author
Dynamic: home-page
Dynamic: license-file
Dynamic: requires-python
